streakgui/__init__.py
streakgui/__main__.py
streakgui/data/experiment.json
streakgui/data/screen.png
streakgui/data/test.hdf5
streakgui/gui/gui.py
streakgui/gui/icons/exit.png
streakgui/gui/icons/icon.png
streakgui/gui/icons/maximize.png
streakgui/gui/icons/minimize.png
streakgui/gui/icons/restore.png
streakgui/gui/ui/stylesheet.qss
sci_streak-0.3.0.dist-info/METADATA
sci_streak-0.3.0.dist-info/WHEEL
sci_streak-0.3.0.dist-info/licenses/LICENSE
sci_streak-0.3.0.dist-info/RECORD
