Metadata-Version: 2.1
Name: sci-streak
Version: 0.3.0
Summary: Python GUI for initial analysis and plotting of Streak Camera data
Project-URL: Homepage, https://github.com/dstrande/sci-streak
Project-URL: Bug Tracker, https://github.com/dstrande/sci-streak/issues
Author-email: Dallas Strandell <dstrande@live.ca>
License:                     GNU GENERAL PUBLIC LICENSE
License-File: LICENSE
Classifier: License :: OSI Approved :: GNU General Public License v3 (GPLv3)
Classifier: Operating System :: Microsoft :: Windows :: Windows 10
Classifier: Programming Language :: Python :: 3
Requires-Python: >=3.9
Requires-Dist: astropy>=5.1
Requires-Dist: h5py>=3.7
Requires-Dist: lmfit>=1.0
Requires-Dist: matplotlib>=3.4
Requires-Dist: numdifftools>=0.9
Requires-Dist: numpy>=1.23
Requires-Dist: pyqtgraph>=0.12
Requires-Dist: pyside6>=6.3
Requires-Dist: scipy>=1.8
